{
  "title": "Gamend",
  "tagline": "Game + Backend",
  "description": "Open source game server with authentication, users, lobbies, groups, friends, notifications, leaderboards, server scripting and admin portal",
  "css": "",
  "logo": "/images/logo.png",
  "banner": "/images/banner.png",
  "favicon": "/favicon.ico",
  "changelog": "/CHANGELOG.md",
  "blog": "/blog",
  "useful_links": [
    { "title": "Discord", "url": "https://discord.com/invite/56dMud8HYn", "icon": "hero-chat-bubble-left-ellipsis" },
    { "title": "Source Code", "url": "https://github.com/appsinacup/game_server", "icon": "hero-book-open" },
    { "title": "Guides", "url": "/docs/setup", "icon": "hero-academic-cap" },
    { "title": "API Docs", "url": "/api/docs", "icon": "hero-book-open" },
    { "title": "Blog", "url": "/blog", "icon": "hero-newspaper" },
    { "title": "Release Notes", "url": "/changelog", "icon": "hero-document-text" }
  ],
  "features": [
    { "title": "Authentication & Users", "description": "Email, Magic-link, OAuth, JWT and Session. Register, login, reset password and verify email.", "icon": "hero-lock-closed" },
    { "title": "Lobbies & Leaderboards", "description": "Customizable settings and real-time updates. Server-authoritative leaderboards.", "icon": "hero-home" },
    { "title": "Friends & Groups", "description": "Request, block, and lists with real-time presence and notifications. Communities with public, private, and hidden visibility.", "icon": "hero-user-group" },
    { "title": "Server Scripting & Server Scheduling", "description": "Server logic using Elixir scripts. Schedule tasks for automated server operations.", "icon": "hero-computer-desktop" },
    { "title": "Persistence & Caching", "description": "SQLite (in memory) and PostgreSQL. In-memory or distributed caching.", "icon": "hero-server-stack" },
    { "title": "Web & Integrations", "description": "Built-in web UI and admin portal. Supports Discord, Apple, Google, Facebook, Steam.", "icon": "hero-puzzle-piece" }
  ]
}
